{
    "primary_language": "en",
    "debugging_mode": true,
    "enable_ppm": false,
    "router": [
        {"path": "/", "page": "index"},
        {"path": "/view/collection", "page": "view_collection"}
    ],
    "libraries": {
        "MongoDB_Driver": {
            "directory_name": "MongoDB-Driver",
            "autoloader": "MongoDB.php",
            "check_class_exists": true,
	    "namespace": "MongoDB",
            "main_class": "MongoDB"
        }
    },
    "runtime_scripts": {
        "initialize": [],
        "on_page_load": [],
        "page_loaded": [],
        "after_request": [],
        "on_request": [],
        "on_import": []
    }
}
